meraki_api/__init__.py
meraki_api/__version__.py
meraki_api/_test.py
meraki_api/admins.py
meraki_api/config_templates.py
meraki_api/devices.py
meraki_api/l3_firewall_rules.py
meraki_api/lazy_requests.py
meraki_api/meraki_api.py
meraki_api/meraki_api_resource.py
meraki_api/networks.py
meraki_api/organizations.py
meraki_api/phone_contacts.py
meraki_api/saml_roles.py
meraki_api/site_to_site_vpn.py
meraki_api/sm.py
meraki_api/ssids.py
meraki_api/static_routes.py
meraki_api/switch_ports.py
meraki_api/utils.py
meraki_api/vlans.py
meraki_api-1.1.2.dist-info/DESCRIPTION.rst
meraki_api-1.1.2.dist-info/METADATA
meraki_api-1.1.2.dist-info/RECORD
meraki_api-1.1.2.dist-info/WHEEL
meraki_api-1.1.2.dist-info/metadata.json
meraki_api-1.1.2.dist-info/top_level.txt
