Metadata-Version: 2.0
Name: meraki-api
Version: 1.1.2
Summary: Meraki Dashboard API wrapper.
Home-page: https://github.com/guzmonne/meraki_api
Author: Guzmán Monné
Author-email: guzmonne@hotmail.com
License: MIT
Download-URL: https://github.com/guzmonne/meraki_api/archive/1.1.2.tar.gz
Keywords: api development
Platform: UNKNOWN
Classifier: Development Status :: 3 - Alpha
Classifier: Intended Audience :: Developers
Classifier: Topic :: Software Development :: Build Tools
Classifier: License :: OSI Approved :: MIT License
Classifier: Programming Language :: Python :: 3
Classifier: Programming Language :: Python :: 3.6
Requires-Dist: requests
